{
	"name": "{{host.name}} consuming more than 90% of system memory",
	"type": "metric alert",
	"query": "avg(last_15m):avg:system.mem.pct_usable{*} by {host} < 0.1",
	"message": "{{host.name}} - {{host.ip}} sustained memory usage is over 90% for the last 15 mins\nPlease use the [system dashboard](https://app.datadoghq.com/screen/487253/system-dashboard--azure) to investigate",
	"tags": [],
	"options": {
		"notify_audit": false,
		"locked": false,
		"timeout_h": 0,
		"silenced": {},
		"include_tags": false,
		"no_data_timeframe": null,
		"new_host_delay": 300,
		"require_full_window": true,
		"notify_no_data": false,
		"renotify_interval": 0,
		"escalation_message": "",
		"thresholds": {
			"critical": 0.1
		}
	}
}
